aempsconn/aemps.py
aempsconn/filter/__init__.py
aempsconn/filter/maestras.py
aempsconn/filter/material.py
aempsconn/filter/medicamento.py
aempsconn/filter/medicamentos.py
aempsconn/filter/nota.py
aempsconn/filter/presentaciones.py
aempsconn/filter/registro_cambios.py
aempsconn/filter/vmpp.py
aempsconn/modules/__init__.py
aempsconn/modules/material.py
aempsconn/modules/medicamento.py
aempsconn/modules/medicamentos.py
aempsconn/modules/notas.py
aempsconn/modules/presentaciones.py
aempsconn/modules/registro_cambios.py
aempsconn/modules/vmpp.py
aempsconn/objects/__init__.py
aempsconn/objects/atc.py
aempsconn/objects/descripcion_clinica.py
aempsconn/objects/documento.py
aempsconn/objects/documento_material.py
aempsconn/objects/estado.py
aempsconn/objects/excipiente.py
aempsconn/objects/foto.py
aempsconn/objects/item.py
aempsconn/objects/material.py
aempsconn/objects/medicamento.py
aempsconn/objects/nota.py
aempsconn/objects/presentacion.py
aempsconn/objects/principio_activo.py
aempsconn/objects/problema_suministro.py
aempsconn/objects/registro_cambios.py
aempsconn/objects/seccion.py
aempsconn/objects/videos.py
aempsconn/utils/constants.py
aempsconn/utils/filter/__init__.py
aempsconn/utils/filter/base_operator.py
aempsconn/utils/filter/filter.py
aempsconn/utils/filter/operator.py
aempsconn/utils/hof.py
aempsconn/utils/module/__init__.py
aempsconn/utils/module/base_module.py
aempsconn/utils/request_handler.py
aempsconn-1.1.1.dist-info/LICENSE
aempsconn-1.1.1.dist-info/METADATA
aempsconn-1.1.1.dist-info/WHEEL
aempsconn-1.1.1.dist-info/RECORD
