Metadata-Version: 2.1
Name: aempsconn
Version: 1.1.1
Summary: Library designed for interacting with the CIMA API (AEMPS)
Home-page: https://github.com/fqlenos/aempsconn
License: MIT
Author: fqlenos
Author-email: fqlenos@protonmail.com
Maintainer: fqlenos
Maintainer-email: fqlenos@protonmail.com
Requires-Python: >=3.10,<4.0
Classifier: License :: OSI Approved :: MIT License
Classifier: Programming Language :: Python :: 3
Classifier: Programming Language :: Python :: 3.10
Classifier: Programming Language :: Python :: 3.11
Classifier: Programming Language :: Python :: 3.12
Classifier: Programming Language :: Python :: 3.13
Requires-Dist: pydantic (==2.10.3)
Requires-Dist: requests (==2.32.3)
Requires-Dist: urllib3 (==2.2.3)
Project-URL: Repository, https://github.com/fqlenos/aempsconn
